{"docs_components_container.md":"bfc953dd","docs_components_code.md":"8116f5f3","docs_components_hr.md":"3e1f0750","docs_components_heading.md":"a5fc72e0","docs_components_head.md":"c198dc7a","docs_components_column.md":"cd4654b6","docs_components_body.md":"78613ecf","docs_components_button.md":"e6647fc0","docs_components_font.md":"ca8c91e3","docs_components_all.md":"1ba30f13","docs_components_link.md":"119a8262","docs_components_html.md":"11cd57bf","docs_components_image.md":"ecafe89b","docs_contributing.md":"33c01bb7","docs_components_markdown.md":"1bb369f8","docs_components_preview.md":"7f0c9e5f","docs_components_section.md":"44c3630f","docs_components_text.md":"f460ba53","docs_core_cli.md":"ca89e1aa","docs_components_tailwind.md":"9e014452","docs_components_row.md":"c4387f42","docs_introduction.md":"4634847f","include_header.md":"6f2b611c","index.md":"5d9834e8","include_readme.md":"20d538c5","include_install.md":"7759a90a","include_contributing.md":"1e1a49af","samples.md":"e64c9dc7","docs_email-providers.md":"8d13fef9","docs_quick-start.md":"1de17a3f","docs_core_render.md":"9e54a347"}
